MANIFEST.in
RELEASE-VERSION
pavement.py
paver-minilib.zip
setup.py
version.py
base_node/__init__.py
base_node/__init__.pyc
base_node/driver.py
base_node/driver.pyc
base_node/Arduino/BaseNode/BaseNode.cpp
base_node/Arduino/BaseNode/BaseNode.h
base_node/Arduino/BaseNode/BaseNode.o
base_node/Arduino/BaseNode/library.properties
base_node/Arduino/BaseNode/examples/basic/SConscript
base_node/Arduino/BaseNode/examples/basic/basic.ino
base_node/firmware/basic.hex
wheeler.base_node.egg-info/PKG-INFO
wheeler.base_node.egg-info/SOURCES.txt
wheeler.base_node.egg-info/dependency_links.txt
wheeler.base_node.egg-info/pbr.json
wheeler.base_node.egg-info/top_level.txt