Metadata-Version: 1.0
Name: wheeler.base-node
Version: 0.4.post1
Summary: Common base class/API for embedded hardware devices.
Home-page: https://github.com/wheeler-microfluidics/base-node
Author: Ryan Fobel
Author-email: ryan@fobel.net
License: GPLv2
Platform: UNKNOWN
